{
    "role_1": "Physicist_RoleType.ASSISTANT",
    "topic;": "Thermodynamics",
    "sub_topic": "Calculation of compressibility factor of a gas",
    "message_1": "A gas is contained in a cylinder of volume 2.5 L at a pressure of 1.2 atm and a temperature of 298 K. Calculate the compressibility factor of the gas assuming it follows the ideal gas law. Is the gas behaving ideally or non-ideally? If non-ideal, what kind of deviation from ideality is expected?",
    "message_2": "The compressibility factor (Z) is a dimensionless quantity that is used to describe the deviation of a real gas from ideal gas behavior. It is defined as the ratio of the molar volume of a real gas to the molar volume of an ideal gas under the same conditions of temperature and pressure. For an ideal gas, Z = 1.\n\nTo calculate the compressibility factor, we first need to find the molar volume of the gas. The ideal gas law is given by:\n\nPV = nRT\n\nWhere P is the pressure, V is the volume, n is the number of moles, R is the ideal gas constant, and T is the temperature.\n\nWe are not given the number of moles (n) in the problem, but we can still find the molar volume by dividing both sides of the ideal gas law equation by n:\n\n(PV) / n = RT\nV / n = RT / P\n\nNow we can plug in the given values:\n\nV / n = (0.0821 L atm / K mol) * (298 K) / (1.2 atm)\n\nV / n = 20.39 L/mol\n\nThe molar volume of the gas is 20.39 L/mol. Now we can calculate the compressibility factor (Z):\n\nZ = (V_real) / (V_ideal)\n\nSince we are assuming the gas follows the ideal gas law, V_real = V_ideal, and:\n\nZ = (20.39 L/mol) / (20.39 L/mol) = 1\n\nThe compressibility factor is 1, which means the gas is behaving ideally under the given conditions. If the compressibility factor were greater than 1, the gas would exhibit positive deviation from ideality (meaning it is less compressible than an ideal gas), and if it were less than 1, the gas would exhibit negative deviation from ideality (meaning it is more compressible than an ideal gas). In this case, there is no deviation from ideality."
}