{
    "role_1": "Physicist_RoleType.ASSISTANT",
    "topic;": "Fluid mechanics",
    "sub_topic": "Fluid instabilities and turbulence modeling",
    "message_1": "A water jet is discharging from a nozzle with a diameter of 5 cm and a velocity of 20 m/s. Determine the Reynolds number and predict whether the flow will be laminar or turbulent. If the flow is predicted to be turbulent, calculate the friction factor and pressure drop per meter of pipe length.",
    "message_2": "To determine the Reynolds number (Re) and predict whether the flow will be laminar or turbulent, we need to use the following formula:\n\nRe = (ρ * V * D) / μ\n\nwhere:\nρ = density of water (approximately 1000 kg/m³ for water at room temperature)\nV = velocity of the water jet (20 m/s)\nD = diameter of the nozzle (0.05 m, since we need to convert 5 cm to meters)\nμ = dynamic viscosity of water (approximately 1 x 10^-3 Pa·s for water at room temperature)\n\nNow, let's calculate the Reynolds number:\n\nRe = (1000 kg/m³ * 20 m/s * 0.05 m) / (1 x 10^-3 Pa·s)\nRe = (1000 * 20 * 0.05) / (0.001)\nRe = 1000000\n\nThe Reynolds number is 1,000,000. Generally, a flow is considered laminar if the Reynolds number is less than 2,000, and turbulent if it's greater than 4,000. Since our Reynolds number is 1,000,000, the flow is predicted to be turbulent.\n\nNow, let's calculate the friction factor (f) using the Colebrook equation for turbulent flow:\n\n1 / √f = -2.0 * log10((ε / (3.7 * D)) + (2.51 / (Re * √f)))\n\nwhere:\nε = roughness of the pipe (assuming smooth pipe, ε = 0)\n\nSince the Colebrook equation is implicit, we can use an approximation method, such as the Swamee-Jain equation, to estimate the friction factor:\n\nf = 0.25 / (log10((ε / (3.7 * D)) + (5.74 / Re^0.9)))^2\n\nSubstituting the values:\n\nf = 0.25 / (log10((0 / (3.7 * 0.05)) + (5.74 / 1000000^0.9)))^2\nf ≈ 0.25 / (log10(5.74 / 1000000^0.9))^2\nf ≈ 0.25 / (log10(0.0185))^2\nf ≈ 0.25 / (-1.732)^2\nf ≈ 0.25 / 2.999\nf ≈ 0.0833\n\nThe friction factor is approximately 0.0833.\n\nNow, let's calculate the pressure drop per meter of pipe length (∆P/L) using the Darcy-Weisbach equation:\n\n∆P/L = f * (ρ * V^2) / (2 * D)\n\nSubstituting the values:\n\n∆P/L = 0.0833 * (1000 kg/m³ * (20 m/s)^2) / (2 * 0.05 m)\n∆P/L = 0.0833 * (1000 * 400) / 0.1\n∆P/L = 0.0833 * 4000000\n∆P/L = 33320 Pa/m\n\nThe pressure drop per meter of pipe length is 33,320 Pa/m."
}