{
    "role_1": "Physicist_RoleType.ASSISTANT",
    "topic;": "Solid state physics",
    "sub_topic": "Investigation of superconductivity in a material",
    "message_1": "How does the critical temperature of a superconducting material change with varying dopant concentration in the material?",
    "message_2": "The critical temperature (Tc) of a superconducting material is the temperature below which the material exhibits superconductivity, i.e., zero electrical resistance. The critical temperature can be influenced by various factors, including the dopant concentration in the material.\n\nDoping is the process of introducing impurities or dopants into a material to modify its properties, such as electrical conductivity or critical temperature. In the case of superconducting materials, dopants can either increase or decrease the critical temperature, depending on the type of dopant and its concentration.\n\nGenerally, there are two main effects of dopants on the critical temperature of superconducting materials:\n\n1. Enhancing superconductivity: In some cases, the introduction of dopants can increase the critical temperature of the material. This is often observed in high-temperature superconductors, such as cuprates and iron-based superconductors. The dopants can enhance superconductivity by optimizing the charge carrier concentration, which leads to stronger electron pairing and a higher Tc.\n\n2. Suppressing superconductivity: In other cases, dopants can decrease the critical temperature of the material. This can occur when the dopants introduce disorder or scattering centers in the material, which can disrupt the electron pairing responsible for superconductivity. Additionally, dopants can also change the electronic structure of the material, leading to a reduction in Tc.\n\nThe relationship between dopant concentration and critical temperature is not always linear and can be quite complex. In some cases, there may be an optimal dopant concentration that maximizes the critical temperature, while in other cases, the critical temperature may decrease monotonically with increasing dopant concentration.\n\nIn summary, the critical temperature of a superconducting material can change with varying dopant concentration, either increasing or decreasing depending on the type of dopant and its concentration. The exact relationship between dopant concentration and critical temperature depends on the specific material and dopant under consideration."
}