{
    "role_1": "Physicist_RoleType.ASSISTANT",
    "topic;": "Plasma physics",
    "sub_topic": "Plasma-based space weather forecasting",
    "message_1": "\"How can the study of plasma physics aid in developing more accurate and timely forecasting of space weather events, such as solar flares and coronal mass ejections, which can potentially disrupt communication systems and endanger astronauts in space?\"",
    "message_2": "The study of plasma physics is crucial in developing more accurate and timely forecasting of space weather events, such as solar flares and coronal mass ejections (CMEs), because these phenomena are primarily governed by the behavior of plasma in the Sun's outer layers. Plasma is a state of matter consisting of charged particles, including ions and free electrons, and its behavior is influenced by both electric and magnetic fields. Understanding the fundamental principles of plasma physics can help us predict and mitigate the effects of space weather events on communication systems and astronaut safety.\n\nHere are some ways in which plasma physics can aid in forecasting space weather events:\n\n1. Understanding magnetic reconnection: Solar flares and CMEs are often triggered by the process of magnetic reconnection, where the magnetic field lines in the Sun's corona break and reconnect, releasing a large amount of energy. Plasma physics helps us understand the underlying mechanisms of magnetic reconnection, allowing us to develop models that can predict when and where these events might occur.\n\n2. Studying plasma instabilities: Plasma instabilities, such as the Kelvin-Helmholtz instability and the Rayleigh-Taylor instability, can lead to the formation of solar flares and CMEs. By studying these instabilities in detail, we can better understand the conditions that lead to the onset of space weather events and develop early warning systems.\n\n3. Investigating the solar wind: The solar wind is a continuous stream of plasma that flows from the Sun's corona into space. It plays a crucial role in shaping the Earth's magnetosphere and can influence the impact of space weather events. By studying the properties and behavior of the solar wind, we can better understand how it interacts with the Earth's magnetic field and develop more accurate forecasts of space weather events.\n\n4. Developing advanced simulation tools: Plasma physics provides the foundation for developing advanced numerical simulation tools that can model the complex behavior of plasma in the Sun's corona and the solar wind. These simulations can help us understand the processes that lead to the formation of solar flares and CMEs, and predict their occurrence and potential impact on Earth.\n\n5. Improving space weather monitoring: A better understanding of plasma physics can lead to the development of more sensitive and accurate instruments for monitoring space weather events. These instruments can provide real-time data on the properties of solar flares and CMEs, allowing for more timely and accurate forecasts.\n\nIn conclusion, the study of plasma physics is essential for improving our ability to forecast space weather events and mitigate their potential impacts on communication systems and astronaut safety. By deepening our understanding of the processes that govern the behavior of plasma in the Sun's outer layers, we can develop more accurate models and early warning systems to protect our technology and astronauts in space."
}