{
    "role_1": "Physicist_RoleType.ASSISTANT",
    "topic;": "Astrophysics",
    "sub_topic": "Solar physics and space weather",
    "message_1": "How does space weather affect the Earth's magnetic field and what are the potential consequences for technological infrastructure such as power grids and communication systems?",
    "message_2": "Space weather refers to the varying conditions in the space environment, particularly the solar wind, which is a stream of charged particles emitted by the Sun. These particles interact with the Earth's magnetic field, causing various effects.\n\nThe Earth's magnetic field is primarily affected by space weather through a process called geomagnetic reconnection. When the solar wind carries a magnetic field with an opposite direction to the Earth's magnetic field, the two fields can merge, allowing energy from the solar wind to enter the Earth's magnetosphere. This can cause geomagnetic storms, which are temporary disturbances in the Earth's magnetic field.\n\nThe potential consequences of space weather on technological infrastructure are mainly due to the induced electric currents in the Earth's atmosphere and on the ground. These induced currents can affect power grids, communication systems, and other technologies that rely on electromagnetic signals.\n\n1. Power grids: Geomagnetic storms can induce currents in power lines, transformers, and other electrical infrastructure. These currents can cause voltage fluctuations, overheating, and even damage to transformers, leading to power outages. In extreme cases, large-scale blackouts can occur, as happened in Quebec, Canada, in 1989.\n\n2. Communication systems: Space weather can affect radio communication systems by altering the ionosphere, a layer of the Earth's atmosphere that reflects and refracts radio waves. Changes in the ionosphere can cause disruptions in high-frequency (HF) radio communication, which is used for aviation, maritime, and military purposes. Additionally, geomagnetic storms can cause increased signal noise in satellite communication systems, leading to degraded performance or temporary outages.\n\n3. Satellite operations: Satellites in Earth's orbit can be exposed to increased levels of radiation during space weather events, which can damage their electronic components and solar panels. This can shorten the lifespan of satellites and cause malfunctions in their systems. Furthermore, geomagnetic storms can cause changes in the density of the upper atmosphere, leading to increased drag on satellites and affecting their orbits.\n\n4. Navigation systems: The Global Positioning System (GPS) and other satellite-based navigation systems rely on precise timing signals from satellites. Space weather can cause delays in the propagation of these signals, leading to errors in position and timing information.\n\n5. Pipeline corrosion: Induced currents from geomagnetic storms can also flow through pipelines, increasing the rate of corrosion and potentially leading to leaks or other structural failures.\n\nTo mitigate the risks associated with space weather, power grid operators, satellite operators, and other stakeholders monitor space weather forecasts and take appropriate measures to protect their systems. This can include adjusting power grid configurations, altering satellite operations, and implementing backup communication systems."
}