{
    "role_1": "Physicist_RoleType.ASSISTANT",
    "topic;": "Condensed matter physics",
    "sub_topic": "Study of nanomaterials and nanotechnology",
    "message_1": "\"What is the effect of the size of gold nanoparticles on their optical properties, specifically their absorption spectra, and how can this information be used in the development of nanotechnology applications?\"",
    "message_2": "The size of gold nanoparticles has a significant effect on their optical properties, particularly their absorption spectra. This is mainly due to a phenomenon known as localized surface plasmon resonance (LSPR). LSPR occurs when the conduction electrons in the gold nanoparticles oscillate collectively in response to an incident electromagnetic field, such as light. The oscillation frequency depends on the size, shape, and surrounding environment of the nanoparticles.\n\nAs the size of gold nanoparticles changes, their absorption spectra shift accordingly. Smaller nanoparticles typically exhibit a blue shift in their absorption spectra, meaning that they absorb light at shorter wavelengths (towards the blue end of the spectrum). Conversely, larger nanoparticles exhibit a red shift in their absorption spectra, absorbing light at longer wavelengths (towards the red end of the spectrum). This size-dependent shift in absorption spectra is due to the changes in the plasmon resonance frequency as the nanoparticle size increases or decreases.\n\nThis information can be used in the development of various nanotechnology applications, such as:\n\n1. Sensing and detection: Gold nanoparticles can be used as highly sensitive and selective sensors for detecting various chemical and biological species. By monitoring the shift in the absorption spectra upon binding of the target molecule, it is possible to detect the presence and concentration of the target analyte.\n\n2. Photothermal therapy: Gold nanoparticles can be used for targeted cancer therapy by exploiting their size-dependent absorption properties. By tuning the size of the nanoparticles to absorb light at specific wavelengths, they can be selectively heated upon exposure to laser light, causing localized destruction of cancer cells without harming healthy tissue.\n\n3. Solar energy conversion: Gold nanoparticles can be used to enhance the efficiency of solar cells by increasing the absorption of light. By incorporating nanoparticles with specific size-dependent absorption properties, it is possible to optimize the absorption of sunlight and improve the overall efficiency of the solar cell.\n\n4. Optical imaging and labeling: Gold nanoparticles can be used as contrast agents in various optical imaging techniques, such as dark-field microscopy and fluorescence imaging. By tuning the size of the nanoparticles, it is possible to achieve optimal contrast and resolution for specific imaging applications.\n\n5. Plasmonic devices: Gold nanoparticles can be used to develop novel plasmonic devices, such as waveguides, antennas, and switches, that rely on the manipulation of light at the nanoscale. By controlling the size and shape of the nanoparticles, it is possible to tailor their optical properties and achieve the desired functionality.\n\nIn summary, understanding the effect of the size of gold nanoparticles on their optical properties, specifically their absorption spectra, is crucial for the development of various nanotechnology applications. By tuning the size of the nanoparticles, it is possible to optimize their optical properties and enhance the performance of the resulting devices and systems."
}