{
    "role_1": "Physicist_RoleType.ASSISTANT",
    "topic;": "Condensed matter physics",
    "sub_topic": "Study of ferroelectric and piezoelectric materials",
    "message_1": "\"How does the crystal structure of a ferroelectric material affect its piezoelectric properties?\"",
    "message_2": "The crystal structure of a ferroelectric material plays a crucial role in determining its piezoelectric properties. Piezoelectricity is the ability of certain materials to generate an electric charge in response to applied mechanical stress, and vice versa. Ferroelectric materials are a specific class of piezoelectric materials that exhibit spontaneous electric polarization, which can be reversed by an external electric field.\n\nThe relationship between the crystal structure and piezoelectric properties of a ferroelectric material can be understood through the following aspects:\n\n1. Unit cell symmetry: The crystal structure of a material is defined by its unit cell, which is the smallest repeating unit in the crystal lattice. For a material to exhibit piezoelectric properties, it must have a non-centrosymmetric unit cell. In other words, the unit cell should not have a center of symmetry. Ferroelectric materials typically have non-centrosymmetric unit cells, which allows them to exhibit piezoelectric behavior.\n\n2. Polarization direction: The spontaneous electric polarization in ferroelectric materials arises due to the displacement of positive and negative ions within the unit cell. This displacement creates a net dipole moment, which is responsible for the piezoelectric effect. The direction of this dipole moment, or polarization, is determined by the crystal structure. In some materials, the polarization direction can be easily switched by an external electric field, leading to strong piezoelectric properties.\n\n3. Domain structure: Ferroelectric materials often consist of multiple domains, which are regions with uniform polarization direction. The domain structure is influenced by the crystal structure, as well as external factors such as temperature and mechanical stress. The movement and reorientation of these domains in response to external stimuli contribute to the piezoelectric properties of the material. Materials with a more favorable domain structure will exhibit stronger piezoelectric effects.\n\n4. Coupling between mechanical and electrical properties: The strength of the piezoelectric effect in a ferroelectric material depends on the coupling between its mechanical and electrical properties. This coupling is determined by the crystal structure, as it influences the efficiency with which mechanical stress is converted into electrical charge, and vice versa. Materials with a strong coupling between these properties will exhibit a higher piezoelectric response.\n\nIn summary, the crystal structure of a ferroelectric material has a significant impact on its piezoelectric properties. The unit cell symmetry, polarization direction, domain structure, and coupling between mechanical and electrical properties are all influenced by the crystal structure, which ultimately determines the strength and efficiency of the piezoelectric effect in the material."
}