{
    "role_1": "Physicist_RoleType.ASSISTANT",
    "topic;": "Quantum field theory",
    "sub_topic": "Calculation of chiral anomalies in quantum field theory.",
    "message_1": "How can the calculation of chiral anomalies be used to explain the behavior of quantum field theories and their symmetries? Provide a detailed analysis of the mathematical basis for these calculations using appropriate examples.",
    "message_2": "Chiral anomalies are a phenomenon in quantum field theories (QFTs) that arise when a classical symmetry is broken at the quantum level. This occurs when a chiral symmetry, which is a symmetry between left-handed and right-handed particles, is not conserved in the quantized version of the theory. The study of chiral anomalies is essential for understanding the behavior of QFTs and their symmetries, as they can lead to important physical consequences, such as the decay of particles that would otherwise be forbidden by classical symmetries.\n\nThe mathematical basis for the calculation of chiral anomalies involves the use of path integrals and the concept of functional determinants. In a QFT, the path integral is a mathematical object that encodes the probability amplitudes for different field configurations. When quantizing a theory with chiral symmetry, one must compute the path integral over both left-handed and right-handed fields. The chiral anomaly arises when the measure of this path integral is not invariant under chiral transformations.\n\nTo see this more explicitly, let's consider a simple example: a massless Dirac fermion field ψ in four-dimensional spacetime. The classical action for this field is given by:\n\nS[ψ, ψ̄] = ∫ d⁴x ψ̄(x) iγ^μ ∂_μ ψ(x),\n\nwhere γ^μ are the Dirac gamma matrices, and ψ̄(x) is the Dirac adjoint of ψ(x). The classical theory has a chiral symmetry, which acts on the fields as:\n\nψ(x) → exp(iαγ^5) ψ(x),\nψ̄(x) → ψ̄(x) exp(iαγ^5),\n\nwhere α is a constant parameter and γ^5 is the fifth gamma matrix. The action is invariant under this transformation, which implies that the chiral current J^μ_5 = ψ̄(x) γ^μ γ^5 ψ(x) is conserved:\n\n∂_μ J^μ_5 = 0.\n\nHowever, when we quantize the theory using the path integral formalism, this symmetry is not preserved. The path integral is given by:\n\nZ = ∫ [dψ][dψ̄] exp(iS[ψ, ψ̄]),\n\nwhere [dψ] and [dψ̄] denote integration over all field configurations. The chiral anomaly arises when we compute the functional determinant of the Dirac operator, which appears in the measure of the path integral. This determinant is not invariant under chiral transformations, leading to a non-conservation of the chiral current at the quantum level:\n\n∂_μ ⟨J^μ_5⟩ ≠ 0.\n\nThe explicit calculation of the chiral anomaly can be done using the Fujikawa method, which involves introducing a regularization scheme to make sense of the functional determinant. This method leads to the famous Adler-Bell-Jackiw (ABJ) anomaly equation:\n\n∂_μ ⟨J^μ_5⟩ = (g^2/16π^2) F^a_μν F̃^a^μν,\n\nwhere g is the coupling constant, F^a_μν is the field strength tensor for the gauge field, and F̃^a^μν is its dual. The right-hand side of this equation is proportional to the topological charge density of the gauge field, which is an integer-valued quantity. This result has important physical implications, such as the decay of the neutral pion (π^0) into two photons, which is allowed by the chiral anomaly despite being forbidden by the classical chiral symmetry.\n\nIn summary, the calculation of chiral anomalies is crucial for understanding the behavior of quantum field theories and their symmetries. The mathematical basis for these calculations involves the use of path integrals and functional determinants, and the explicit computation of anomalies can be done using regularization techniques such as the Fujikawa method. The study of chiral anomalies has led to important insights into the properties of elementary particles and their interactions, as well as the structure of QFTs in general."
}