{
    "role_1": "Physicist_RoleType.ASSISTANT",
    "topic;": "Quantum computing",
    "sub_topic": "Quantum computing with topological insulators",
    "message_1": "Consider a topological insulator based quantum computer. The qubits are realized as Majorana fermions confined to a superconducting wire that is placed on the surface of the topological insulator. Suppose that there are five qubits, and each qubit can be independently controlled by applying a magnetic field. If we want to perform a quantum Fourier transform on the state of these qubits, how many gates/actions do we need to implement to successfully perform this transform? What is the total running time required for this quantum Fourier transform?",
    "message_2": "To perform a quantum Fourier transform (QFT) on a 5-qubit system, we need to implement a series of Hadamard gates and controlled phase rotation gates. The general formula for the number of gates required to perform a QFT on an n-qubit system is (n * (n + 1)) / 2. In our case, with 5 qubits, the number of gates required is (5 * (5 + 1)) / 2 = 15 gates.\n\nThe total running time of the QFT depends on the time it takes to perform each gate and the time it takes to apply the magnetic field to control the qubits. Let's assume that the time to perform a single gate is T_gate and the time to apply the magnetic field is T_field. Since we have 15 gates, the total running time for the QFT would be 15 * T_gate + 5 * T_field.\n\nHowever, without specific information about the time it takes to perform a gate and apply the magnetic field in this topological insulator-based quantum computer, we cannot provide an exact value for the total running time."
}